README.md
setup.py
metaculus/__init__.py
metaculus/api.py
metaculus/utils.py
metaculus.egg-info/PKG-INFO
metaculus.egg-info/SOURCES.txt
metaculus.egg-info/dependency_links.txt
metaculus.egg-info/not-zip-safe
metaculus.egg-info/requires.txt
metaculus.egg-info/top_level.txt