Metadata-Version: 2.1
Name: metaculus
Version: 0.0.1
Summary: Metaculus controller.
Home-page: https://gitlab.com/wefindx/metaculus
Author: Mindey
Author-email: mindey@qq.com
License: ASK FOR PERMISSIONS
Platform: UNKNOWN
Provides-Extra: test
